{"inkVersion":21,"root":[[{"->":"main"},["done",{"#f":5,"#n":"g-0"}],null],"done",{"main":[["^The sea is endless, almost hypnotic. I could lose myself in its vastness...","#","^speaker:Dannte ","/#","#","^portrait:default","/#","\n","^But this peace, it's deceptive.","#","^speaker:Juan ","/#","#","^portrait:red","/#","\n","^There's something about this night that feels... off.","#","^speaker:Nico ","/#","#","^portrait:blue","/#","\n","ev","str","^Walk away","/str","/ev",{"*":".^.c-0","flg":20},"ev","str","^Stay","/str","/ev",{"*":".^.c-1","flg":20},{"c-0":["\n","^You walked away ","#","^changeState:moved","/#","\n","done",{"#f":5}],"c-1":["\n","^You stayed ","#","^changeState:stayed","/#","\n","done","end",{"#f":5}]}],{"#f":1}],"#f":1}],"listDefs":{}}